odoo/addons/github_connector_oca/README.rst
odoo/addons/github_connector_oca/__init__.py
odoo/addons/github_connector_oca/__manifest__.py
odoo/addons/github_connector_oca/i18n/github_connector_oca.pot
odoo/addons/github_connector_oca/models/__init__.py
odoo/addons/github_connector_oca/models/odoo_module_version.py
odoo/addons/github_connector_oca/readme/CONTRIBUTORS.rst
odoo/addons/github_connector_oca/readme/DESCRIPTION.rst
odoo/addons/github_connector_oca/readme/USAGE.rst
odoo/addons/github_connector_oca/static/description/icon.png
odoo/addons/github_connector_oca/static/description/index.html
odoo/addons/github_connector_oca/views/odoo_module_version.xml
odoo13_addon_github_connector_oca-13.0.1.0.1.dev2.dist-info/METADATA
odoo13_addon_github_connector_oca-13.0.1.0.1.dev2.dist-info/WHEEL
odoo13_addon_github_connector_oca-13.0.1.0.1.dev2.dist-info/top_level.txt
odoo13_addon_github_connector_oca-13.0.1.0.1.dev2.dist-info/RECORD
