Metadata-Version: 2.1
Name: odoo13-addon-github-connector-oca
Version: 13.0.1.0.1.dev2
Summary: Add OCA specific information to Odoo modules
Home-page: https://github.com/OCA/interface-github
Author: Odoo Community Association (OCA), Road-Support
Author-email: support@odoo-community.org
License: AGPL-3
Platform: UNKNOWN
Classifier: Programming Language :: Python
Classifier: Framework :: Odoo
Classifier: Framework :: Odoo :: 13.0
Classifier: License :: OSI Approved :: GNU Affero General Public License v3
Requires-Python: >=3.5
Requires-Dist: odoo13-addon-github-connector-odoo
Requires-Dist: odoo <13.1dev,>=13.0a
